qdrant_txtai/__init__.py
qdrant_txtai/ann/__init__.py
qdrant_txtai/ann/qdrant.py
qdrant_txtai-2.0.0.dist-info/LICENSE
qdrant_txtai-2.0.0.dist-info/METADATA
qdrant_txtai-2.0.0.dist-info/WHEEL
qdrant_txtai-2.0.0.dist-info/RECORD
