Metadata-Version: 2.1
Name: qdrant-txtai
Version: 2.0.0
Summary: An integration of Qdrant ANN vector database backend with txtai
License: Apache 2.0
Author: Kacper Łukawski
Author-email: kacper.lukawski@qdrant.com
Requires-Python: >=3.8,<=3.13
Classifier: License :: Other/Proprietary License
Classifier: Programming Language :: Python :: 3
Classifier: Programming Language :: Python :: 3.8
Classifier: Programming Language :: Python :: 3.9
Classifier: Programming Language :: Python :: 3.10
Classifier: Programming Language :: Python :: 3.11
Classifier: Programming Language :: Python :: 3.12
Requires-Dist: qdrant-client (>=1.9.1,<2.0.0)
Requires-Dist: txtai (>=5.0.0)
